paramarea/__init__.py
paramarea/myfunc.py
paramarea-0.1.0.dist-info/METADATA
paramarea-0.1.0.dist-info/WHEEL
paramarea-0.1.0.dist-info/top_level.txt
paramarea-0.1.0.dist-info/RECORD
