Metadata-Version: 2.1
Name: paramarea
Version: 0.1.0
Summary: This library is capable of calculating area and circumference/perimeter of circle and rectangle. 
Author: Girmada
